MANIFEST.in
__init__.py
setup.py
use_rsa - Copie.py
use_rsa.py
use_rsa/__init__.py
use_rsa/setup.py
use_rsa/use_rsa.py
use_rsa.egg-info/PKG-INFO
use_rsa.egg-info/SOURCES.txt
use_rsa.egg-info/dependency_links.txt
use_rsa.egg-info/top_level.txt